doorpj_test/__init__.py
doorpj_test/hi.py
doorpj_test-0.0.5.dist-info/LICENSE
doorpj_test-0.0.5.dist-info/METADATA
doorpj_test-0.0.5.dist-info/WHEEL
doorpj_test-0.0.5.dist-info/top_level.txt
doorpj_test-0.0.5.dist-info/RECORD
