Metadata-Version: 2.1
Name: doorpj-test
Version: 0.0.5
Summary: Can use it to save or recall preferences from Python.
Home-page: https://github.com/ParkJiyong/doorpj_test
Author: ParkJiyong
Author-email: hptbutcld@gmail.com
License: UNKNOWN
Platform: UNKNOWN
Classifier: License :: OSI Approved :: MIT License
License-File: LICENSE
Requires-Dist: py4j (==0.10.9.2)
